wsiloader/__init__.py
wsiloader/wsi_dataloader.py
wsiloader/wsi_index_dataset.py
wsiloader-0.0.2.dist-info/LICENSE
wsiloader-0.0.2.dist-info/METADATA
wsiloader-0.0.2.dist-info/WHEEL
wsiloader-0.0.2.dist-info/top_level.txt
wsiloader-0.0.2.dist-info/RECORD
