Metadata-Version: 2.1
Name: wsiloader
Version: 0.0.2
Summary: An efficient PyTorch dataloader for working with Whole-Slide Images
Home-page: https://github.com/gafaua/wsi-dataloader
Author: Gaspar Faure
License: MIT
License-File: LICENSE
Requires-Dist: torch
Requires-Dist: torchvision
Requires-Dist: pillow
Requires-Dist: numpy
